{
  "9391593": {
    "rowidx": 6,
    "silence": "FALSE",
    "num": "190",
    "manDept": "SHG",
    "notes": "",
    "quarter": "22Q2",
    "numDept": "3",
    "mapStatus": "1",
    "mtsid": "372234",
    "name": "RCC Europe",
    "mmsi": "311003100",
    "length": "199.9",
    "breadth": "32.26",
    "grossTonnage": "57,692",
    "dept": "CN SHG",
    "deptLong": "Shanghai",
    "deptType": "ATD",
    "deptLocalTime": "2022/05/20 02:20",
    "deptTime": "2022/05/19 18:20",
    "dest": "SG SIN",
    "destLong": "Singapore",
    "destType": "ETA",
    "destLocalTime": "2022/05/26 03:00",
    "destTime": "2022/05/25 19:00",
    "position": "30.53485\u00b0 / 122.1817\u00b0",
    "area": "East China Sea",
    "status": "Underway using Engine"
  },
  "9722302": {
    "rowidx": 7,
    "silence": "FALSE",
    "num": "189",
    "manDept": "SHG",
    "notes": "",
    "quarter": "22Q2",
    "numDept": "2",
    "mapStatus": "2",
    "mtsid": "4018974",
    "name": "Theben",
    "mmsi": "566044000",
    "length": "199.97",
    "breadth": "36.5",
    "grossTonnage": "75,283",
    "dept": "CN SHG",
    "deptLong": "Shanghai",
    "deptType": "ATD",
    "deptLocalTime": "2022/05/15 22:42",
    "deptTime": "2022/05/15 14:42",
    "dest": "SG SIN",
    "destLong": "Singapore",
    "destType": "ETA",
    "destLocalTime": "2022/05/22 06:00",
    "destTime": "2022/05/21 22:00",
    "position": "21.88573\u00b0 / 121.184\u00b0",
    "area": "South China",
    "status": "Out of Range"
  },
  "9702431": {
    "rowidx": 8,
    "silence": "FALSE",
    "num": "188",
    "manDept": "SHG",
    "notes": "",
    "quarter": "22Q2",
    "numDept": "1",
    "mapStatus": "2",
    "mtsid": "1508269",
    "name": "Glovis Splendor",
    "mmsi": "538005960",
    "length": "199.97",
    "breadth": "35",
    "grossTonnage": "64,751",
    "dept": "CN SHG",
    "deptLong": "Shanghai",
    "deptType": "ATD",
    "deptLocalTime": "2022/05/11 05:53",
    "deptTime": "2022/05/10 21:53",
    "dest": "EG SUZ",
    "destLong": "Suez Canal",
    "destType": "ETA",
    "destLocalTime": "2022/05/28 19:00",
    "destTime": "2022/05/28 17:00",
    "position": "4.781579\u00b0 / 98.93098\u00b0",
    "area": "Malacca Strait",
    "status": "Out of Range"
  },
  "9158276": {
    "rowidx": 210,
    "silence": "FALSE",
    "num": "-14",
    "manDept": "SHG",
    "notes": "",
    "quarter": "22Q2",
    "numDept": "0",
    "mapStatus": "4",
    "mtsid": "414305",
    "name": "Aquarius Leader",
    "mmsi": "373630000",
    "length": "199.93",
    "breadth": "32.26",
    "grossTonnage": "58,329",
    "dept": "TR KFZ",
    "deptLong": "Korfez",
    "deptType": "ATD",
    "deptLocalTime": "2022/05/05 05:54",
    "deptTime": "2022/05/05 02:54",
    "dest": "SG SIN",
    "destLong": "Singapore",
    "destType": "ETA",
    "destLocalTime": "2022/05/23 15:00",
    "destTime": "2022/05/23 07:00",
    "position": "5.653572\u00b0 / 80.37762\u00b0",
    "area": "Laccadive Sea",
    "status": "Out of Range"
  },
  "9515008": {
    "rowidx": 211,
    "silence": "FALSE",
    "num": "-15",
    "manDept": "SHG",
    "notes": "",
    "quarter": "22Q2",
    "numDept": "0",
    "mapStatus": "4",
    "mtsid": "732771",
    "name": "Viking Sea",
    "mmsi": "538009734",
    "length": "167.25",
    "breadth": "28",
    "grossTonnage": "39,454",
    "dept": "SI KOP",
    "deptLong": "Koper",
    "deptType": "ATD",
    "deptLocalTime": "2022/05/16 23:34",
    "deptTime": "2022/05/16 21:34",
    "dest": "EG SUZ",
    "destLong": "Suez Canal",
    "destType": "ETA",
    "destLocalTime": "2022/05/20 22:00",
    "destTime": "2022/05/20 20:00",
    "position": "33.86817\u00b0 / 25.95082\u00b0",
    "area": "East Mediterranean",
    "status": "Underway using Engine"
  },
  "9338852": {
    "rowidx": 212,
    "silence": "FALSE",
    "num": "-16",
    "manDept": "SHG",
    "notes": "",
    "quarter": "22Q2",
    "numDept": "0",
    "mapStatus": "4",
    "mtsid": "372666",
    "name": "Sunshine Ace",
    "mmsi": "311015100",
    "length": "199.95",
    "breadth": "32.2",
    "grossTonnage": "58,917",
    "dept": "GB PRU",
    "deptLong": "Portbury",
    "deptType": "ATD",
    "deptLocalTime": "2022/05/15 05:35",
    "deptTime": "2022/05/15 04:35",
    "dest": "DE EME",
    "destLong": "Emden",
    "destType": "ATA",
    "destLocalTime": "2022/05/19 03:45",
    "destTime": "2022/05/19 01:45",
    "position": "53.33458\u00b0 / 7.162153\u00b0",
    "area": "North Sea",
    "status": "Moored"
  },
  "9318474": {
    "rowidx": 213,
    "silence": "FALSE",
    "num": "-17",
    "manDept": "SHG",
    "notes": "",
    "quarter": "22Q2",
    "numDept": "0",
    "mapStatus": "4",
    "mtsid": "312575",
    "name": "Hoegh Bangkok",
    "mmsi": "258720000",
    "length": "199.9",
    "breadth": "32.29",
    "grossTonnage": "55,775",
    "dept": "IT LIV",
    "deptLong": "Livorno",
    "deptType": "ATD",
    "deptLocalTime": "2022/05/14 21:01",
    "deptTime": "2022/05/14 19:01",
    "dest": "BE ZEE",
    "destLong": "Zeebrugge",
    "destType": "ETA",
    "destLocalTime": "2022/05/21 06:00",
    "destTime": "2022/05/21 04:00",
    "position": "49.91659\u00b0 / -2.437578\u00b0",
    "area": "English Channel",
    "status": "Underway using Engine"
  },
  "9277838": {
    "rowidx": 214,
    "silence": "FALSE",
    "num": "-18",
    "manDept": "SHG",
    "notes": "",
    "quarter": "22Q2",
    "numDept": "0",
    "mapStatus": "4",
    "mtsid": "375351",
    "name": "Ivory Arrow",
    "mmsi": "311696000",
    "length": "199.96",
    "breadth": "32.4",
    "grossTonnage": "57,718",
    "dept": "GR PIR",
    "deptLong": "Piraeus",
    "deptType": "ATD",
    "deptLocalTime": "2022/05/18 07:20",
    "deptTime": "2022/05/18 04:20",
    "dest": "IT LIV",
    "destLong": "Livorno",
    "destType": "ETA",
    "destLocalTime": "2022/05/20 10:00",
    "destTime": "2022/05/20 08:00",
    "position": "41.242\u00b0 / 11.36379\u00b0",
    "area": "Tyrrhenian Sea",
    "status": "Underway using Engine"
  },
  "9531715": {
    "rowidx": 215,
    "silence": "FALSE",
    "num": "-19",
    "manDept": "SHG",
    "notes": "",
    "quarter": "22Q2",
    "numDept": "0",
    "mapStatus": "4",
    "mtsid": "464025",
    "name": "Bess",
    "mmsi": "372995000",
    "length": "199.98",
    "breadth": "32.26",
    "grossTonnage": "58,750",
    "dept": "TH LCH",
    "deptLong": "Laem Chabang",
    "deptType": "ATD",
    "deptLocalTime": "2022/05/01 19:33",
    "deptTime": "2022/05/01 12:33",
    "dest": "BE ZEE",
    "destLong": "Zeebrugge",
    "destType": "ETA",
    "destLocalTime": "2022/05/26 09:00",
    "destTime": "2022/05/26 07:00",
    "position": "34.74277\u00b0 / 22.3216\u00b0",
    "area": "East Mediterranean",
    "status": "Underway using Engine"
  },
  "9561253": {
    "rowidx": 216,
    "silence": "FALSE",
    "num": "-20",
    "manDept": "SHG",
    "notes": "",
    "quarter": "22Q2",
    "numDept": "0",
    "mapStatus": "4",
    "mtsid": "384343",
    "name": "Tranquil Ace",
    "mmsi": "353943000",
    "length": "199.95",
    "breadth": "32.2",
    "grossTonnage": "58,939",
    "dept": "GR PIR",
    "deptLong": "Piraeus",
    "deptType": "ATD",
    "deptLocalTime": "2022/05/19 14:18",
    "deptTime": "2022/05/19 11:18",
    "dest": "IT LIV",
    "destLong": "Livorno",
    "destType": "ETA",
    "destLocalTime": "2022/05/21 16:00",
    "destTime": "2022/05/21 14:00",
    "position": "36.3446\u00b0 / 21.809\u00b0",
    "area": "Aegean Sea",
    "status": "Underway using Engine"
  },
  "9782089": {
    "rowidx": 217,
    "silence": "FALSE",
    "num": "-21",
    "manDept": "SHG",
    "notes": "",
    "quarter": "22Q2",
    "numDept": "0",
    "mapStatus": "4",
    "mtsid": "5350368",
    "name": "Thruxton",
    "mmsi": "636018347",
    "length": "199.96",
    "breadth": "38",
    "grossTonnage": "72,684",
    "dept": "CN SHG",
    "deptLong": "Shanghai",
    "deptType": "ATD",
    "deptLocalTime": "2022/05/02 01:17",
    "deptTime": "2022/05/01 17:17",
    "dest": "EG SUEZ SOUTH ANCH",
    "destLong": "Suez Canal",
    "destType": "ATA",
    "destLocalTime": "2022/05/19 18:28",
    "destTime": "2022/05/19 16:28",
    "position": "29.8397\u00b0 / 32.56583\u00b0",
    "area": "Red Sea",
    "status": "At Anchor"
  },
  "9312482": {
    "rowidx": 218,
    "silence": "FALSE",
    "num": "-22",
    "manDept": "SHG",
    "notes": "",
    "quarter": "22Q2",
    "numDept": "0",
    "mapStatus": "4",
    "mtsid": "312657",
    "name": "Hoegh Shanghai",
    "mmsi": "258758000",
    "length": "228.74",
    "breadth": "32.29",
    "grossTonnage": "68,871",
    "dept": "CN SHG",
    "deptLong": "Shanghai",
    "deptType": "ATD",
    "deptLocalTime": "2022/05/07 15:23",
    "deptTime": "2022/05/07 07:23",
    "dest": "EG SUZ",
    "destLong": "Suez Canal",
    "destType": "ETA",
    "destLocalTime": "2022/05/26 22:00",
    "destTime": "2022/05/26 20:00",
    "position": "5.630617\u00b0 / 80.15775\u00b0",
    "area": "Laccadive Sea",
    "status": "Out of Range"
  },
  "9731640": {
    "rowidx": 219,
    "silence": "FALSE",
    "num": "-23",
    "manDept": "SHG",
    "notes": "",
    "quarter": "22Q2",
    "numDept": "0",
    "mapStatus": "4",
    "mtsid": "5971530",
    "name": "Tannhauser",
    "mmsi": "265827240",
    "length": "199.9",
    "breadth": "36",
    "grossTonnage": "73,358",
    "dept": "CN SHG",
    "deptLong": "Shanghai",
    "deptType": "ATD",
    "deptLocalTime": "2022/05/08 04:10",
    "deptTime": "2022/05/07 20:10",
    "dest": "EG SUZ",
    "destLong": "Suez Canal",
    "destType": "ETA",
    "destLocalTime": "2022/05/25 20:00",
    "destTime": "2022/05/25 18:00",
    "position": "5.911482\u00b0 / 80.20847\u00b0",
    "area": "East Asia",
    "status": "Out of Range"
  },
  "9531741": {
    "rowidx": 220,
    "silence": "FALSE",
    "num": "-24",
    "manDept": "SHG",
    "notes": "",
    "quarter": "22Q2",
    "numDept": "0",
    "mapStatus": "4",
    "mtsid": "665474",
    "name": "Asteria Leader",
    "mmsi": "431024000",
    "length": "199.94",
    "breadth": "32.26",
    "grossTonnage": "63,084",
    "dept": "SG SIN",
    "deptLong": "Singapore",
    "deptType": "ATD",
    "deptLocalTime": "2022/05/17 17:58",
    "deptTime": "2022/05/17 09:58",
    "dest": "IN PAV",
    "destLong": "Pipavav",
    "destType": "ETA",
    "destLocalTime": "2022/05/17 02:43",
    "destTime": "2022/05/16 18:43",
    "position": "3.136902\u00b0 / 100.6877\u00b0",
    "area": "Malacca Strait",
    "status": "Out of Range"
  },
  "9610406": {
    "rowidx": 221,
    "silence": "FALSE",
    "num": "-25",
    "manDept": "SHG",
    "notes": "",
    "quarter": "22Q2",
    "numDept": "0",
    "mapStatus": "4",
    "mtsid": "418892",
    "name": "Victorious Ace",
    "mmsi": "431605000",
    "length": "199.95",
    "breadth": "32.2",
    "grossTonnage": "59,598",
    "dept": "SG SIN",
    "deptLong": "Singapore",
    "deptType": "ATD",
    "deptLocalTime": "2022/05/16 17:23",
    "deptTime": "2022/05/16 09:23",
    "dest": "EG SUZ",
    "destLong": "Suez Canal",
    "destType": "ETA",
    "destLocalTime": "2022/05/27 23:00",
    "destTime": "2022/05/27 21:00",
    "position": "4.23166\u00b0 / 99.58168\u00b0",
    "area": "Malacca Strait",
    "status": "Out of Range"
  },
  "9338620": {
    "rowidx": 222,
    "silence": "FALSE",
    "num": "-26",
    "manDept": "SHG",
    "notes": "",
    "quarter": "22Q2",
    "numDept": "0",
    "mapStatus": "4",
    "mtsid": "370155",
    "name": "Swallow Ace",
    "mmsi": "309509000",
    "length": "199.95",
    "breadth": "32.2",
    "grossTonnage": "58,685",
    "dept": "CN SHG",
    "deptLong": "Shanghai",
    "deptType": "ATD",
    "deptLocalTime": "2022/05/11 21:01",
    "deptTime": "2022/05/11 13:01",
    "dest": "EG SUZ",
    "destLong": "Suez Canal",
    "destType": "ETA",
    "destLocalTime": "2022/05/30 00:01",
    "destTime": "2022/05/29 22:01",
    "position": "5.422302\u00b0 / 98.12173\u00b0",
    "area": "Malacca Strait",
    "status": "Underway using Engine"
  },
  "9777838": {
    "rowidx": 223,
    "silence": "FALSE",
    "num": "-27",
    "manDept": "SHG",
    "notes": "",
    "quarter": "22Q2",
    "numDept": "0",
    "mapStatus": "4",
    "mtsid": "5834600",
    "name": "Dugong Ace",
    "mmsi": "353453000",
    "length": "199.95",
    "breadth": "32",
    "grossTonnage": "63,116",
    "dept": "CN SHG",
    "deptLong": "Shanghai",
    "deptType": "ATD",
    "deptLocalTime": "2022/05/14 10:27",
    "deptTime": "2022/05/14 02:27",
    "dest": "SG SIN",
    "destLong": "Singapore",
    "destType": "ETA",
    "destLocalTime": "2022/05/20 17:00",
    "destTime": "2022/05/20 09:00",
    "position": "22.77563\u00b0 / 119.2614\u00b0",
    "area": "South China",
    "status": "Out of Range"
  },
  "9432919": {
    "rowidx": 224,
    "silence": "FALSE",
    "num": "-28",
    "manDept": "SHG",
    "notes": "",
    "quarter": "22Q2",
    "numDept": "0",
    "mapStatus": "4",
    "mtsid": "733550",
    "name": "Lake Como",
    "mmsi": "636020885",
    "length": "182.8",
    "breadth": "31.5",
    "grossTonnage": "47,168",
    "dept": "CN XMG",
    "deptLong": "Xiamen",
    "deptType": "ATD",
    "deptLocalTime": "2022/05/19 07:59",
    "deptTime": "2022/05/18 23:59",
    "dest": "CN XMG",
    "destLong": "Xiamen",
    "destType": "ETA",
    "destLocalTime": "2022/05/17 06:37",
    "destTime": "2022/05/16 22:37",
    "position": "23.5342\u00b0 / 118.1502\u00b0",
    "area": "South China",
    "status": "Underway using Engine"
  },
  "9392341": {
    "rowidx": 225,
    "silence": "FALSE",
    "num": "-29",
    "manDept": "SHG",
    "notes": "",
    "quarter": "22Q2",
    "numDept": "0",
    "mapStatus": "4",
    "mtsid": "459362",
    "name": "Venus Leader",
    "mmsi": "431824000",
    "length": "186.03",
    "breadth": "28.2",
    "grossTonnage": "42,160",
    "dept": "CN SHG",
    "deptLong": "Shanghai",
    "deptType": "ATD",
    "deptLocalTime": "2022/05/15 23:16",
    "deptTime": "2022/05/15 15:16",
    "dest": "SG SIN",
    "destLong": "Singapore",
    "destType": "ETA",
    "destLocalTime": "2022/05/22 06:00",
    "destTime": "2022/05/21 22:00",
    "position": "22.79517\u00b0 / 119.617\u00b0",
    "area": "South China",
    "status": "Out of Range"
  },
  "9472206": {
    "rowidx": 226,
    "silence": "FALSE",
    "num": "-30",
    "manDept": "SHG",
    "notes": "",
    "quarter": "22Q2",
    "numDept": "0",
    "mapStatus": "4",
    "mtsid": "858533",
    "name": "Grand Uranus",
    "mmsi": "477142300",
    "length": "232.39",
    "breadth": "32.26",
    "grossTonnage": "72,408",
    "dept": "CN SHG",
    "deptLong": "Shanghai",
    "deptType": "ATD",
    "deptLocalTime": "2022/05/20 02:45",
    "deptTime": "2022/05/19 18:45",
    "dest": "CN TXG",
    "destLong": "Tianjin",
    "destType": "ETA",
    "destLocalTime": "2022/05/22 03:30",
    "destTime": "2022/05/21 19:30",
    "position": "31.18322\u00b0 / 122.1695\u00b0",
    "area": "East China Sea",
    "status": "Underway using Engine"
  },
  "9397987": {
    "rowidx": 227,
    "silence": "FALSE",
    "num": "-31",
    "manDept": "SHG",
    "notes": "",
    "quarter": "22Q2",
    "numDept": "0",
    "mapStatus": "4",
    "mtsid": "385530",
    "name": "Aquamarine Ace",
    "mmsi": "352980798",
    "length": "199.99",
    "breadth": "32.26",
    "grossTonnage": "60,143",
    "dept": "CN SHG",
    "deptLong": "Shanghai",
    "deptType": "ATD",
    "deptLocalTime": "2022/05/20 03:32",
    "deptTime": "2022/05/19 19:32",
    "dest": "CN XMG",
    "destLong": "Xiamen",
    "destType": "ETA",
    "destLocalTime": "2022/05/22 06:00",
    "destTime": "2022/05/21 22:00",
    "position": "31.25055\u00b0 / 121.9659\u00b0",
    "area": "East China Sea",
    "status": "Underway using Engine"
  }
}