{
  "9673020": {
    "rowidx": 6,
    "num": "167",
    "manDept": "SHG",
    "notes": "",
    "quarter": "21Q4",
    "numDept": "19",
    "mapStatus": "2",
    "mtsid": "3391300",
    "name": "Viking Bravery",
    "mmsi": "565806000",
    "length": "199.9",
    "breadth": "34.9",
    "grossTonnage": "62,106",
    "dept": "CN SHG",
    "deptLong": "Shanghai",
    "deptType": "ATD",
    "deptLocalTime": "2021/11/20 00:35",
    "deptTime": "2021/11/19 16:35",
    "dest": "EG SUZ",
    "destLong": "Suez Canal",
    "destType": "ETA",
    "destLocalTime": "2021/12/07 21:00",
    "destTime": "2021/12/07 19:00",
    "position": "16.70333\u00b0 / 40.88333\u00b0",
    "area": "Laccadive Sea",
    "status": "Out of Range"
  },
  "9293648": {
    "rowidx": 7,
    "num": "166",
    "manDept": "SHG",
    "notes": "",
    "quarter": "21Q4",
    "numDept": "18",
    "mapStatus": "2",
    "mtsid": "409092",
    "name": "Paradise Ace",
    "mmsi": "352142000",
    "length": "199.99",
    "breadth": "32.26",
    "grossTonnage": "60,175",
    "dept": "CN SHG",
    "deptLong": "Shanghai",
    "deptType": "ATD",
    "deptLocalTime": "2021/11/16 11:19",
    "deptTime": "2021/11/16 03:19",
    "dest": "GB SOU",
    "destLong": "Southampton",
    "destType": "ETA",
    "destLocalTime": "2021/12/03 22:19",
    "destTime": "2021/12/03 20:19",
    "position": "34.1598\u00b0 / 23.45943\u00b0",
    "area": "East Mediterranean",
    "status": "Underway using Engine"
  },
  "9355238": {
    "rowidx": 8,
    "num": "165",
    "manDept": "SHG",
    "notes": "",
    "quarter": "21Q4",
    "numDept": "17",
    "mapStatus": "2",
    "mtsid": "416239",
    "name": "Grand Dahlia",
    "mmsi": "355222000",
    "length": "199.9",
    "breadth": "32.26",
    "grossTonnage": "59,217",
    "dept": "CN SHG",
    "deptLong": "Shanghai",
    "deptType": "ATD",
    "deptLocalTime": "2021/11/14 09:51",
    "deptTime": "2021/11/14 01:51",
    "dest": "GB SOU",
    "destLong": "Southampton",
    "destType": "ETA",
    "destLocalTime": "2021/12/02 19:40",
    "destTime": "2021/12/02 17:40",
    "position": "36.33503\u00b0 / 14.85498\u00b0",
    "area": "Ionian Sea",
    "status": "Underway using Engine"
  },
  "9210438": {
    "rowidx": 9,
    "num": "164",
    "manDept": "SHG",
    "notes": "",
    "quarter": "21Q4",
    "numDept": "16",
    "mapStatus": "2",
    "mtsid": "369106",
    "name": "Platinum Ray",
    "mmsi": "308726000",
    "length": "199.98",
    "breadth": "32.27",
    "grossTonnage": "57,772",
    "dept": "KR MAS",
    "deptLong": "Masan",
    "deptType": "ATD",
    "deptLocalTime": "2021/11/23 18:19",
    "deptTime": "2021/11/23 09:19",
    "dest": "EG SUZ",
    "destLong": "Suez Canal",
    "destType": "ETA",
    "destLocalTime": "2021/12/09 21:00",
    "destTime": "2021/12/09 19:00",
    "position": "12.73186\u00b0 / 58.47975\u00b0",
    "area": "Laccadive Sea",
    "status": "Out of Range"
  },
  "9441520": {
    "rowidx": 10,
    "num": "163",
    "manDept": "SHG",
    "notes": "",
    "quarter": "21Q4",
    "numDept": "15",
    "mapStatus": "3",
    "mtsid": "373460",
    "name": "Horizon Leader",
    "mmsi": "311040600",
    "length": "199.95",
    "breadth": "32.29",
    "grossTonnage": "58,767",
    "dept": "GB SOU",
    "deptLong": "Southampton",
    "deptType": "ATD",
    "deptLocalTime": "2021/11/06 13:38",
    "deptTime": "2021/11/06 05:38",
    "dest": "BE ZEE",
    "destLong": "Zeebrugge",
    "destType": "ATA",
    "destLocalTime": "2021/12/05 20:31",
    "destTime": "2021/12/05 19:31",
    "position": "51.33357\u00b0 / 3.217652\u00b0",
    "area": "North Sea",
    "status": "Stopped"
  },
  "9690559": {
    "rowidx": 11,
    "num": "162",
    "manDept": "SHG",
    "notes": "",
    "quarter": "21Q4",
    "numDept": "14",
    "mapStatus": "3",
    "mtsid": "3553106",
    "name": "Hyperion Ray",
    "mmsi": "311000322",
    "length": "199.97",
    "breadth": "35.43",
    "grossTonnage": "71,177",
    "dept": "GB SOU",
    "deptLong": "Southampton",
    "deptType": "ATD",
    "deptLocalTime": "2021/12/03 05:49",
    "deptTime": "2021/12/03 04:49",
    "dest": "IL ASH",
    "destLong": "Ashdod",
    "destType": "ETA",
    "destLocalTime": "2021/12/16 22:00",
    "destTime": "2021/12/16 20:00",
    "position": "50.85887\u00b0 / -1.35593\u00b0",
    "area": "English Channel",
    "status": "Underway using Engine"
  },
  "9684990": {
    "rowidx": 12,
    "num": "161",
    "manDept": "SHG",
    "notes": "",
    "quarter": "21Q4",
    "numDept": "13",
    "mapStatus": "2",
    "mtsid": "6701824",
    "name": "Hoegh Tracer",
    "mmsi": "258628000",
    "length": "199.9",
    "breadth": "40.8",
    "grossTonnage": "76,420",
    "dept": "IT LIV",
    "deptLong": "Livorno",
    "deptType": "ATD",
    "deptLocalTime": "2021/12/01 01:31",
    "deptTime": "2021/12/01 00:31",
    "dest": "ES SDR",
    "destLong": "Santander",
    "destType": "ETA",
    "destLocalTime": "2021/12/06 05:30",
    "destTime": "2021/12/06 04:30",
    "position": "44.08315\u00b0 / -5.77989\u00b0",
    "area": "Biscay Bay",
    "status": "Underway using Engine"
  },
  "9279812": {
    "rowidx": 187,
    "num": "-14",
    "manDept": "SHG",
    "notes": "",
    "quarter": "21Q4",
    "numDept": "0",
    "mapStatus": "4",
    "mtsid": "713302",
    "name": "Neptune Koper",
    "mmsi": "215940000",
    "length": "196.4",
    "breadth": "31.1",
    "grossTonnage": "44,408",
    "dept": "IT LIV",
    "deptLong": "Livorno",
    "deptType": "ATD",
    "deptLocalTime": "2021/12/03 19:33",
    "deptTime": "2021/12/03 18:33",
    "dest": "GR PIR",
    "destLong": "Piraeus",
    "destType": "ETA",
    "destLocalTime": "2021/12/06 06:00",
    "destTime": "2021/12/06 04:00",
    "position": "36.36454\u00b0 / 22.69974\u00b0",
    "area": "Aegean Sea",
    "status": "Underway using Engine"
  },
  "9409481": {
    "rowidx": 188,
    "num": "-15",
    "manDept": "SHG",
    "notes": "",
    "quarter": "21Q4",
    "numDept": "0",
    "mapStatus": "4",
    "mtsid": "386635",
    "name": "Sanderling Ace",
    "mmsi": "538007573",
    "length": "199.95",
    "breadth": "32.2",
    "grossTonnage": "58,685",
    "dept": "EG ALY",
    "deptLong": "Alexandria",
    "deptType": "ATD",
    "deptLocalTime": "2021/12/03 05:26",
    "deptTime": "2021/12/03 03:26",
    "dest": "GR PIR",
    "destLong": "Piraeus",
    "destType": "ATA",
    "destLocalTime": "2021/12/05 17:12",
    "destTime": "2021/12/05 15:12",
    "position": "37.95878\u00b0 / 23.60515\u00b0",
    "area": "Piraeus Area",
    "status": "Moored"
  },
  "9748289": {
    "rowidx": 189,
    "num": "-16",
    "manDept": "SHG",
    "notes": "",
    "quarter": "21Q4",
    "numDept": "0",
    "mapStatus": "4",
    "mtsid": "4621185",
    "name": "Brooklands",
    "mmsi": "636017767",
    "length": "199.96",
    "breadth": "38",
    "grossTonnage": "72,700",
    "dept": "AE JEA",
    "deptLong": "Jebel Ali",
    "deptType": "ATD",
    "deptLocalTime": "2021/12/02 15:06",
    "deptTime": "2021/12/02 11:06",
    "dest": "SA DMM",
    "destLong": "Dammam",
    "destType": "ATA",
    "destLocalTime": "2021/12/05 08:31",
    "destTime": "2021/12/05 05:31",
    "position": "26.49302\u00b0 / 50.20557\u00b0",
    "area": "Persian Gulf",
    "status": "Moored"
  },
  "9138525": {
    "rowidx": 190,
    "num": "-17",
    "manDept": "SHG",
    "notes": "",
    "quarter": "21Q4",
    "numDept": "0",
    "mapStatus": "4",
    "mtsid": "728889",
    "name": "Don Quijote",
    "mmsi": "564753000",
    "length": "227.9",
    "breadth": "32.29",
    "grossTonnage": "67,141",
    "dept": "CN SHG",
    "deptLong": "Shanghai",
    "deptType": "ATD",
    "deptLocalTime": "2021/11/12 05:56",
    "deptTime": "2021/11/11 21:56",
    "dest": "BE ZEE",
    "destLong": "Zeebrugge",
    "destType": "ETA",
    "destLocalTime": "2021/12/12 00:30",
    "destTime": "2021/12/11 23:30",
    "position": "36.2662\u00b0 / -3.554663\u00b0",
    "area": "Gibraltar",
    "status": "Underway using Engine"
  },
  "9176565": {
    "rowidx": 191,
    "num": "-18",
    "manDept": "SHG",
    "notes": "",
    "quarter": "21Q4",
    "numDept": "0",
    "mapStatus": "4",
    "mtsid": "726076",
    "name": "Boheme",
    "mmsi": "563262000",
    "length": "227",
    "breadth": "32",
    "grossTonnage": "67,264",
    "dept": "CN SHG",
    "deptLong": "Shanghai",
    "deptType": "ATD",
    "deptLocalTime": "2021/11/15 10:15",
    "deptTime": "2021/11/15 02:15",
    "dest": "GB BRS",
    "destLong": "Bristol",
    "destType": "ETA",
    "destLocalTime": "2021/12/04 05:36",
    "destTime": "2021/12/04 03:36",
    "position": "34.37982\u00b0 / 23.63862\u00b0",
    "area": "East Mediterranean",
    "status": "Underway using Engine"
  },
  "9782091": {
    "rowidx": 192,
    "num": "-19",
    "manDept": "SHG",
    "notes": "",
    "quarter": "21Q4",
    "numDept": "0",
    "mapStatus": "4",
    "mtsid": "5433911",
    "name": "Lydden",
    "mmsi": "636018494",
    "length": "199.96",
    "breadth": "38",
    "grossTonnage": "72,684",
    "dept": "SG SIN",
    "deptLong": "Singapore",
    "deptType": "ATD",
    "deptLocalTime": "2021/11/25 06:29",
    "deptTime": "2021/11/24 22:29",
    "dest": "JO AQJ",
    "destLong": "Aqaba",
    "destType": "ETA",
    "destLocalTime": "2021/12/08 02:01",
    "destTime": "2021/12/08 00:01",
    "position": "13.67751\u00b0 / 58.16521\u00b0",
    "area": "Laccadive Sea",
    "status": "Out of Range"
  },
  "9176395": {
    "rowidx": 193,
    "num": "-20",
    "manDept": "SHG",
    "notes": "",
    "quarter": "21Q4",
    "numDept": "0",
    "mapStatus": "4",
    "mtsid": "308302",
    "name": "Hoegh Transporter",
    "mmsi": "257712000",
    "length": "199.98",
    "breadth": "32.26",
    "grossTonnage": "57,757",
    "dept": "CN SHG",
    "deptLong": "Shanghai",
    "deptType": "ATD",
    "deptLocalTime": "2021/11/21 02:14",
    "deptTime": "2021/11/20 18:14",
    "dest": "EG SUZ",
    "destLong": "Suez Canal",
    "destType": "ETA",
    "destLocalTime": "2021/12/10 22:00",
    "destTime": "2021/12/10 20:00",
    "position": "13.67067\u00b0 / 55.72650\u00b0",
    "area": "Laccadive Sea",
    "status": "Out of Range"
  },
  "9427952": {
    "rowidx": 194,
    "num": "-21",
    "manDept": "SHG",
    "notes": "",
    "quarter": "21Q4",
    "numDept": "0",
    "mapStatus": "4",
    "mtsid": "204311",
    "name": "Pagna",
    "mmsi": "236111884",
    "length": "182.9",
    "breadth": "31.79",
    "grossTonnage": "47,057",
    "dept": "CN XMG",
    "deptLong": "Xiamen",
    "deptType": "ATD",
    "deptLocalTime": "2021/11/24 22:19",
    "deptTime": "2021/11/24 14:19",
    "dest": "IL ETH",
    "destLong": "Eilat",
    "destType": "ETA",
    "destLocalTime": "2021/12/14 08:00",
    "destTime": "2021/12/14 06:00",
    "position": "9.44998\u00b0 / 70.91164\u00b0",
    "area": "Laccadive Sea",
    "status": "Out of Range"
  },
  "9483786": {
    "rowidx": 195,
    "num": "-22",
    "manDept": "SHG",
    "notes": "",
    "quarter": "21Q4",
    "numDept": "0",
    "mapStatus": "4",
    "mtsid": "365110",
    "name": "Arabian Sea",
    "mmsi": "538007767",
    "length": "182.8",
    "breadth": "31.74",
    "grossTonnage": "46,800",
    "dept": "CN SHG",
    "deptLong": "Shanghai",
    "deptType": "ATD",
    "deptLocalTime": "2021/11/26 04:02",
    "deptTime": "2021/11/25 20:02",
    "dest": "EG SUZ",
    "destLong": "Suez Canal",
    "destType": "ETA",
    "destLocalTime": "2021/12/16 23:00",
    "destTime": "2021/12/16 21:00",
    "position": "6.31135\u00b0 / 94.78337\u00b0",
    "area": "Malacca Strait",
    "status": "Out of Range"
  },
  "9318515": {
    "rowidx": 196,
    "num": "-23",
    "manDept": "SHG",
    "notes": "",
    "quarter": "21Q4",
    "numDept": "0",
    "mapStatus": "4",
    "mtsid": "369021",
    "name": "Morning Menad",
    "mmsi": "440253000",
    "length": "176.02",
    "breadth": "31.1",
    "grossTonnage": "41,192",
    "dept": "SG SIN",
    "deptLong": "Singapore",
    "deptType": "ATD",
    "deptLocalTime": "2021/12/05 21:20",
    "deptTime": "2021/12/05 13:20",
    "dest": "ID JKT",
    "destLong": "Jakarta",
    "destType": "ETA",
    "destLocalTime": "2021/12/07 07:00",
    "destTime": "2021/12/07 00:00",
    "position": "1.288295\u00b0 / 104.3106\u00b0",
    "area": "Singapore Area",
    "status": "Underway using Engine"
  },
  "9122655": {
    "rowidx": 197,
    "num": "-24",
    "manDept": "SHG",
    "notes": "",
    "quarter": "21Q4",
    "numDept": "0",
    "mapStatus": "4",
    "mtsid": "731714",
    "name": "Don Carlos",
    "mmsi": "566088000",
    "length": "227.9",
    "breadth": "32.29",
    "grossTonnage": "67,141",
    "dept": "CN XMG",
    "deptLong": "Xiamen",
    "deptType": "ATD",
    "deptLocalTime": "2021/12/03 22:18",
    "deptTime": "2021/12/03 14:18",
    "dest": "EG SUZ",
    "destLong": "Suez Canal",
    "destType": "ETA",
    "destLocalTime": "2021/12/20 16:00",
    "destTime": "2021/12/20 14:00",
    "position": "16.08666\u00b0 / 113.33999\u00b0",
    "area": "East China Sea",
    "status": "Out of Range"
  },
  "9536959": {
    "rowidx": 198,
    "num": "-25",
    "manDept": "SHG",
    "notes": "",
    "quarter": "21Q4",
    "numDept": "0",
    "mapStatus": "4",
    "mtsid": "1040669",
    "name": "Delhi Highway",
    "mmsi": "355488000",
    "length": "199.91",
    "breadth": "32.26",
    "grossTonnage": "58,997",
    "dept": "CN SHG",
    "deptLong": "Shanghai",
    "deptType": "ATD",
    "deptLocalTime": "2021/12/01 22:33",
    "deptTime": "2021/12/01 14:33",
    "dest": "SG SIN",
    "destLong": "Singapore",
    "destType": "ETA",
    "destLocalTime": "2021/11/30 19:25",
    "destTime": "2021/11/30 11:25",
    "position": "25.03098\u00b0 / 120.0373\u00b0",
    "area": "East China Sea",
    "status": "Out of Range"
  },
  "9712644": {
    "rowidx": 199,
    "num": "-26",
    "manDept": "SHG",
    "notes": "",
    "quarter": "21Q4",
    "numDept": "0",
    "mapStatus": "4",
    "mtsid": "3658066",
    "name": "Hamburg Highway",
    "mmsi": "431262000",
    "length": "199.96",
    "breadth": "38",
    "grossTonnage": "75,206",
    "dept": "CN SHG",
    "deptLong": "Shanghai",
    "deptType": "ATD",
    "deptLocalTime": "2021/12/03 22:54",
    "deptTime": "2021/12/03 14:54",
    "dest": "CN NSA",
    "destLong": "Nansha",
    "destType": "ETA",
    "destLocalTime": "2021/12/06 06:00",
    "destTime": "2021/12/05 22:00",
    "position": "22.90024\u00b0 / 119.3746\u00b0",
    "area": "South China",
    "status": "Underway using Engine"
  },
  "9722302": {
    "rowidx": 200,
    "num": "-27",
    "manDept": "SHG",
    "notes": "",
    "quarter": "21Q4",
    "numDept": "0",
    "mapStatus": "4",
    "mtsid": "4018974",
    "name": "Theben",
    "mmsi": "566044000",
    "length": "199.97",
    "breadth": "36.5",
    "grossTonnage": "75,283",
    "dept": "AU BNE",
    "deptLong": "Brisbane",
    "deptType": "ATD",
    "deptLocalTime": "2021/11/25 02:51",
    "deptTime": "2021/11/24 16:51",
    "dest": "CN SHG",
    "destLong": "Shanghai",
    "destType": "ATA",
    "destLocalTime": "2021/12/05 00:19",
    "destTime": "2021/12/04 16:19",
    "position": "31.32218\u00b0 / 121.6817\u00b0",
    "area": "East China Sea",
    "status": "Moored"
  },
  "9690523": {
    "rowidx": 201,
    "num": "-28",
    "manDept": "SHG",
    "notes": "",
    "quarter": "21Q4",
    "numDept": "0",
    "mapStatus": "4",
    "mtsid": "1120219",
    "name": "Harvest Leader",
    "mmsi": "311000187",
    "length": "199.97",
    "breadth": "35.4",
    "grossTonnage": "71,177",
    "dept": "SG SIN",
    "deptLong": "Singapore",
    "deptType": "ATD",
    "deptLocalTime": "2021/11/28 18:56",
    "deptTime": "2021/11/28 10:56",
    "dest": "CN SHG",
    "destLong": "Shanghai",
    "destType": "ATA",
    "destLocalTime": "2021/12/05 12:57",
    "destTime": "2021/12/05 04:57",
    "position": "31.32355\u00b0 / 121.6797\u00b0",
    "area": "East China Sea",
    "status": "Moored"
  }
}