{
  "9441582": {
    "rowidx": 6,
    "silence": "FALSE",
    "num": "333",
    "manDept": "SHG",
    "madeIn": "CHN",
    "notes": "",
    "quarter": "23Q2",
    "numDept": "29",
    "mapStatus": "3",
    "mtsid": "373705",
    "name": "Glovis Clipper",
    "mmsi": "311054400",
    "length": "199.99",
    "breadth": "32.29",
    "grossTonnage": "58,767",
    "dept": "LK HBA",
    "deptLong": "Hambantota",
    "deptType": "ATD",
    "deptLocalTime": "2023/08/20 04:11",
    "deptTime": "2023/08/19 20:11",
    "dest": "SA JED",
    "destLong": "Jeddah",
    "destType": "ETA",
    "destLocalTime": "2023/08/30 18:00",
    "destTime": "2023/08/30 15:00",
    "position": "",
    "area": "Malacca Strait",
    "status": "19.2 kn / 308 \u00b0"
  },
  "9706994": {
    "rowidx": 7,
    "silence": "FALSE",
    "num": "332",
    "manDept": "SHG",
    "madeIn": "CHN",
    "notes": "",
    "quarter": "23Q3",
    "numDept": "20",
    "mapStatus": "3",
    "mtsid": "2002390",
    "name": "Glovis Crown",
    "mmsi": "538005981",
    "length": "199.98",
    "breadth": "32",
    "grossTonnage": "59,968",
    "dept": "CN TXG",
    "deptLong": "Tianjin",
    "deptType": "ATD",
    "deptLocalTime": "2023/08/22 08:55",
    "deptTime": "2023/08/22 00:55",
    "dest": "KR MOK",
    "destLong": "Mokpo",
    "destType": "ATA",
    "destLocalTime": "2023/08/24 06:21",
    "destTime": "2023/08/23 21:21",
    "position": "",
    "area": "Yellow Sea",
    "status": "0 kn / 138 \u00b0"
  },
  "9798404": {
    "rowidx": 8,
    "silence": "FALSE",
    "num": "331",
    "manDept": "SHG",
    "madeIn": "CHN",
    "notes": "",
    "quarter": "23Q3",
    "numDept": "19",
    "mapStatus": "3",
    "mtsid": "5114092",
    "name": "Glovis Sky",
    "mmsi": "538007439",
    "length": "229.97",
    "breadth": "32",
    "grossTonnage": "72,269",
    "dept": "CN YTG",
    "deptLong": "Yantai",
    "deptType": "ATD",
    "deptLocalTime": "2023/08/19 17:45",
    "deptTime": "2023/08/19 09:45",
    "dest": "PA BLB",
    "destLong": "Balboa",
    "destType": "ETA",
    "destLocalTime": "2023/09/08 10:00",
    "destTime": "2023/09/08 15:00",
    "position": "",
    "area": "Japan Coast",
    "status": "18.0 kn / 62 \u00b0"
  },
  "9336074": {
    "rowidx": 9,
    "silence": "FALSE",
    "num": "330",
    "manDept": "SHG",
    "madeIn": "CHN",
    "notes": "",
    "quarter": "23Q3",
    "numDept": "18",
    "mapStatus": "2",
    "mtsid": "463978",
    "name": "Morning Composer",
    "mmsi": "371659000",
    "length": "199.97",
    "breadth": "32.26",
    "grossTonnage": "57,542",
    "dept": "US TIW",
    "deptLong": "Tacoma",
    "deptType": "ATD",
    "deptLocalTime": "2023/08/17 03:37",
    "deptTime": "2023/08/17 10:37",
    "dest": "CA BIN",
    "destLong": "Vancouver Anch",
    "destType": "ATA",
    "destLocalTime": "2023/08/22 01:26",
    "destTime": "2023/08/22 08:26",
    "position": "",
    "area": "West Coast Canada",
    "status": "0 kn / 220 \u00b0"
  },
  "9325790": {
    "rowidx": 10,
    "silence": "FALSE",
    "num": "329",
    "manDept": "SHG",
    "madeIn": "CHN",
    "notes": "",
    "quarter": "23Q3",
    "numDept": "17",
    "mapStatus": "2",
    "mtsid": "463620",
    "name": "Dream Diva",
    "mmsi": "372856000",
    "length": "186",
    "breadth": "28.2",
    "grossTonnage": "41,662",
    "dept": "CN SHG",
    "deptLong": "Shanghai",
    "deptType": "ATD",
    "deptLocalTime": "2023/08/18 02:06",
    "deptTime": "2023/08/17 18:06",
    "dest": "",
    "destLong": "",
    "destType": "",
    "destLocalTime": "",
    "destTime": "",
    "position": "",
    "area": "Japan Coast",
    "status": "14.4 kn / 60 \u00b0"
  },
  "9070450": {
    "rowidx": 11,
    "silence": "FALSE",
    "num": "328",
    "manDept": "SHG",
    "madeIn": "CHN",
    "notes": "",
    "quarter": "23Q3",
    "numDept": "16",
    "mapStatus": "2",
    "mtsid": "732444",
    "name": "Turandot",
    "mmsi": "257269000",
    "length": "199.11",
    "breadth": "32.29",
    "grossTonnage": "55,598",
    "dept": "CN SHG",
    "deptLong": "Shanghai",
    "deptType": "ATD",
    "deptLocalTime": "2023/08/11 07:38",
    "deptTime": "2023/08/10 23:38",
    "dest": "AU BNE",
    "destLong": "Brisbane",
    "destType": "ETA",
    "destLocalTime": "2023/08/21 23:30",
    "destTime": "2023/08/21 13:30",
    "position": "",
    "area": "East Australia",
    "status": "0.2 kn / 93 \u00b0"
  },
  "9285483": {
    "rowidx": 12,
    "silence": "FALSE",
    "num": "327",
    "manDept": "SHG",
    "madeIn": "CHN",
    "notes": "",
    "quarter": "23Q3",
    "numDept": "15",
    "mapStatus": "2",
    "mtsid": "306612",
    "name": "Hoegh Tokyo",
    "mmsi": "257408000",
    "length": "228.7",
    "breadth": "32.29",
    "grossTonnage": "68,871",
    "dept": "CN TAG",
    "deptLong": "Taicang",
    "deptType": "ATD",
    "deptLocalTime": "2023/07/25 11:15",
    "deptTime": "2023/07/25 03:15",
    "dest": "IT LIV",
    "destLong": "Livorno",
    "destType": "ETA",
    "destLocalTime": "2023/08/20 17:00",
    "destTime": "2023/08/20 15:00",
    "position": "",
    "area": "Ligurean Sea",
    "status": "0.5 kn / 55 \u00b0"
  },
  "9338709": {
    "rowidx": 13,
    "silence": "FALSE",
    "num": "326",
    "manDept": "SHG",
    "madeIn": "CHN",
    "notes": "",
    "quarter": "23Q3",
    "numDept": "14",
    "mapStatus": "3",
    "mtsid": "407592",
    "name": "Morning Carina",
    "mmsi": "351392000",
    "length": "199.94",
    "breadth": "32.26",
    "grossTonnage": "60,876",
    "dept": "BE ANR",
    "deptLong": "Antwerp",
    "deptType": "ATA",
    "deptLocalTime": "2023/08/24 06:11",
    "deptTime": "2023/08/24 04:11",
    "dest": "DE BRV",
    "destLong": "Bremerhaven",
    "destType": "ETA",
    "destLocalTime": "2023/08/27 21:00",
    "destTime": "2023/08/27 19:00",
    "position": "",
    "area": "Antwerp Area",
    "status": "0 kn / 160 \u00b0"
  },
  "9777814": {
    "rowidx": 16,
    "silence": "FALSE",
    "num": "323",
    "manDept": "SHG",
    "madeIn": "CHN",
    "notes": "",
    "quarter": "23Q3",
    "numDept": "12",
    "mapStatus": "3",
    "mtsid": "5144957",
    "name": "Orca Ace",
    "mmsi": "371563000",
    "length": "199.95",
    "breadth": "32.24",
    "grossTonnage": "63,116",
    "dept": "AU BNE",
    "deptLong": "Brisbane",
    "deptType": "ATD",
    "deptLocalTime": "2023/08/03 00:32",
    "deptTime": "2023/08/02 14:32",
    "dest": "AU MEL",
    "destLong": "Melbourne",
    "destType": "ATA",
    "destLocalTime": "2023/08/22 02:34",
    "destTime": "2023/08/21 16:34",
    "position": "",
    "area": "East Australia",
    "status": "0 kn / 71 \u00b0"
  },
  "9441594": {
    "rowidx": 17,
    "silence": "FALSE",
    "num": "322",
    "manDept": "SHG",
    "madeIn": "CHN",
    "notes": "",
    "quarter": "23Q3",
    "numDept": "11",
    "mapStatus": "3",
    "mtsid": "3557933",
    "name": "Glovis Caravel",
    "mmsi": "311054300",
    "length": "199.99",
    "breadth": "32.29",
    "grossTonnage": "58,767",
    "dept": "AU BNE",
    "deptLong": "Brisbane",
    "deptType": "ATD",
    "deptLocalTime": "2023/08/19 18:54",
    "deptTime": "2023/08/19 08:54",
    "dest": "AU PKL",
    "destLong": "Port Kembla",
    "destType": "ETA",
    "destLocalTime": "2023/08/21 03:00",
    "destTime": "2023/08/20 17:00",
    "position": "",
    "area": "East Australia",
    "status": "1.0 kn / 146 \u00b0"
  }
}